twigi/__init__.py
twigi/early_stopper.py
twigi/load_data.py
twigi/loss.py
twigi/negative_sampler.py
twigi/run_exp.py
twigi/run_from_checkpoint.py
twigi/trainer.py
twigi/twig_nn.py
twigi/twigi.py
twigi/utils.py
twigi-1.0.10.dist-info/METADATA
twigi-1.0.10.dist-info/WHEEL
twigi-1.0.10.dist-info/top_level.txt
twigi-1.0.10.dist-info/RECORD
