Metadata-Version: 2.1
Name: twigi
Version: 1.0.10
Summary: TWIG-I: Embedding-free, treansfer-learning, enabled link prediction using graph topology :D
Home-page: https://github.com/Jeffrey-Sardina
Author: Jeffrey Seathrún Sardina
Author-email: jeffrey.sardina@gmail.com
License: CC BY-NC-SA 4.0
Classifier: Programming Language :: Python :: 3
Classifier: Operating System :: OS Independent
Requires-Dist: numpy ==2.0.0
Requires-Dist: torch
Requires-Dist: torchvision
Requires-Dist: torchaudio
Requires-Dist: torcheval
Requires-Dist: pykeen
Requires-Dist: frozendict
